dayhoff/__init__.py
dayhoff/activation_checkpointing.py
dayhoff/collators.py
dayhoff/constants.py
dayhoff/datasets.py
dayhoff/losses.py
dayhoff/model.py
dayhoff/samplers.py
dayhoff/tokenizers.py
dayhoff/utils.py
dayhoff-0.0.5.dist-info/licenses/LICENSE
dayhoff-0.0.5.dist-info/METADATA
dayhoff-0.0.5.dist-info/WHEEL
dayhoff-0.0.5.dist-info/top_level.txt
dayhoff-0.0.5.dist-info/RECORD
