Metadata-Version: 2.4
Name: dayhoff
Version: 0.0.5
Summary: Python package for generation of protein sequences and evolutionary alignments via discrete diffusion models
Author: Sarah A. Alamdari, Neil Tenenholtz, Samir Char, Kaeli Kaymak-Loveless, Alex J. Lee, Garyk Brixi, Carles Domingo-Enrich, Nicolo Fusi
Author-email: "Kevin K. Yang" <kevyan@microsoft.com>, "Ava P. Amini" <ava.amini@microsoft.com>
License-Expression: MIT
Project-URL: Homepage, https://github.com/microsoft/dayhoff
Project-URL: Repository, https://github.com/microsoft/dayhoff
Project-URL: Issues, https://github.com/microsoft/dayhoff/issues
Project-URL: HuggingFaceDatasets, https://huggingface.co/datasets/microsoft/DayhoffDataset
Project-URL: HuggingFaceModels, https://huggingface.co/microsoft/Dayhoff
Classifier: Programming Language :: Python :: 3
Classifier: Programming Language :: Python :: 3.10
Classifier: Operating System :: OS Independent
Requires-Python: >=3.10.16
License-File: LICENSE
Requires-Dist: pandas~=2.2.3
Requires-Dist: numpy~=1.26.4
Requires-Dist: mdanalysis~=2.7.0
Requires-Dist: python-dotenv~=1.0.1
Requires-Dist: matplotlib~=3.10.1
Requires-Dist: seaborn~=0.13.2
Requires-Dist: h5py~=3.13.0
Requires-Dist: scikit-learn~=1.5.0
Requires-Dist: scipy~=1.15.2
Requires-Dist: torch-geometric~=2.5.2
Requires-Dist: torch-scatter~=2.1.2
Requires-Dist: transformers~=4.42.4
Requires-Dist: datasets~=3.2.0
Requires-Dist: biopython~=1.83
Requires-Dist: blosum~=2.0.3
Requires-Dist: fair-esm~=2.0.0
Requires-Dist: evodiff~=1.1.0
Requires-Dist: sequence-models~=1.8.0
Requires-Dist: pdb-tools~=2.5.0
Requires-Dist: wandb~=0.16.6
Requires-Dist: tqdm~=4.67.1
Requires-Dist: ijson~=3.3.0
Requires-Dist: pyfastx~=2.2.0
Requires-Dist: huggingface_hub~=0.27.1
Requires-Dist: azure-identity~=1.21.0
Dynamic: license-file
